XuexiAngularjs1X/README.md
XuexiAngularjs1X/__init__.py
XuexiAngularjs1X/__main__.py
XuexiAngularjs1X/file.epub
XuexiAngularjs1X/index.html
XuexiAngularjs1X/css/__init__.py
XuexiAngularjs1X/css/annotations.css
XuexiAngularjs1X/css/main.css
XuexiAngularjs1X/css/normalize.css
XuexiAngularjs1X/css/popup.css
XuexiAngularjs1X/font/__init__.py
XuexiAngularjs1X/font/fontello.eot
XuexiAngularjs1X/font/fontello.svg
XuexiAngularjs1X/font/fontello.ttf
XuexiAngularjs1X/font/fontello.woff
XuexiAngularjs1X/img/__init__.py
XuexiAngularjs1X/img/annotator-glyph-sprite.png
XuexiAngularjs1X/img/annotator-icon-sprite.png
XuexiAngularjs1X/img/apple-touch-icon.png
XuexiAngularjs1X/img/cancelfullscreen.png
XuexiAngularjs1X/img/close.png
XuexiAngularjs1X/img/fullscreen.png
XuexiAngularjs1X/img/loader.gif
XuexiAngularjs1X/img/menu-icon.png
XuexiAngularjs1X/img/save.png
XuexiAngularjs1X/img/saved.png
XuexiAngularjs1X/img/settings-s.png
XuexiAngularjs1X/img/settings.png
XuexiAngularjs1X/img/star.png
XuexiAngularjs1X/js/__init__.py
XuexiAngularjs1X/js/epub.js
XuexiAngularjs1X/js/epub.min.js
XuexiAngularjs1X/js/epub.min.map
XuexiAngularjs1X/js/hooks.min.js
XuexiAngularjs1X/js/hooks.min.map
XuexiAngularjs1X/js/reader.js
XuexiAngularjs1X/js/reader.js.map
XuexiAngularjs1X/js/reader.min.js
XuexiAngularjs1X/js/reader.min.map
XuexiAngularjs1X/js/hooks/__init__.py
XuexiAngularjs1X/js/hooks/extensions/__init__.py
XuexiAngularjs1X/js/hooks/extensions/highlight.js
XuexiAngularjs1X/js/libs/__init__.py
XuexiAngularjs1X/js/libs/jquery.min.js
XuexiAngularjs1X/js/libs/localforage.min.js
XuexiAngularjs1X/js/libs/screenfull.js
XuexiAngularjs1X/js/libs/screenfull.min.js
XuexiAngularjs1X/js/libs/zip.min.js
XuexiAngularjs1X/js/plugins/__init__.py
XuexiAngularjs1X/js/plugins/hypothesis.js
XuexiAngularjs1X/js/plugins/search.js
xuexi_angularjs_1_x-2024.3.3.0.dist-info/METADATA
xuexi_angularjs_1_x-2024.3.3.0.dist-info/WHEEL
xuexi_angularjs_1_x-2024.3.3.0.dist-info/entry_points.txt
xuexi_angularjs_1_x-2024.3.3.0.dist-info/top_level.txt
xuexi_angularjs_1_x-2024.3.3.0.dist-info/RECORD
